django_celery_tasks/__init__.py
django_celery_tasks/admin.py
django_celery_tasks/apps.py
django_celery_tasks/managers.py
django_celery_tasks/models.py
django_celery_tasks/task.py
django_celery_tasks/utils.py
django_celery_tasks/backends/__init__.py
django_celery_tasks/backends/cache.py
django_celery_tasks/backends/database.py
django_celery_tasks/middleware/__init__.py
django_celery_tasks/middleware/globalrequestmiddleware.py
django_celery_tasks/migrations/0001_initial.py
django_celery_tasks/migrations/__init__.py
django_celery_tasks-0.0.1.dist-info/DESCRIPTION.rst
django_celery_tasks-0.0.1.dist-info/METADATA
django_celery_tasks-0.0.1.dist-info/RECORD
django_celery_tasks-0.0.1.dist-info/WHEEL
django_celery_tasks-0.0.1.dist-info/entry_points.txt
django_celery_tasks-0.0.1.dist-info/metadata.json
django_celery_tasks-0.0.1.dist-info/top_level.txt
